epcpm/__build.py
epcpm/__init__.py
epcpm/__main__.py
epcpm/__version.py
epcpm/_build.py
epcpm/_version.py
epcpm/c.py
epcpm/canmodel.py
epcpm/cantosym.py
epcpm/cli/__init__.py
epcpm/cli/convertepp.py
epcpm/cli/exportdocx.py
epcpm/cli/exportsym.py
epcpm/cli/importsym.py
epcpm/cli/main.py
epcpm/cli/parameterstoc.py
epcpm/cli/utils.py
epcpm/icon.ico
epcpm/icon.png
epcpm/icon.svg
epcpm/importexport.py
epcpm/importexportdialog.py
epcpm/importexportdialog.ui
epcpm/mainwindow.py
epcpm/mainwindow.ui
epcpm/parameterstoc.py
epcpm/parameterstodocx.py
epcpm/parameterstohierarchy.py
epcpm/parameterstointerface.py
epcpm/parameterstosil.py
epcpm/project.py
epcpm/smdx.py
epcpm/smdxtosunspec.py
epcpm/staticmodbusmodel.py
epcpm/sunspecmodel.py
epcpm/sunspectobitfieldsc.py
epcpm/sunspectomanualc.py
epcpm/sunspectomanualh.py
epcpm/sunspectotablesc.py
epcpm/sunspectoxlsx.py
epcpm/symtoproject.py
epcpm/tests/__init__.py
epcpm/tests/cli/test_parameterstoc.pmp
epcpm/tests/cli/test_parameterstoc.py
epcpm/tests/cli/test_parameterstoc_can.json
epcpm/tests/cli/test_parameterstoc_parameters.json
epcpm/tests/example_can.json
epcpm/tests/example_parameters.json
epcpm/tests/example_project.pmp
epcpm/tests/project/can.json
epcpm/tests/project/parameters.json
epcpm/tests/project/project.pmp
epcpm/tests/project/staticmodbus.json
epcpm/tests/project/sunspec.json
epcpm/tests/sunspec/MODBUS_SunSpec-EPC.xlsx
epcpm/tests/sunspec/smdx_00001.xml
epcpm/tests/sunspec/smdx_00017.xml
epcpm/tests/sunspec/smdx_00103.xml
epcpm/tests/sunspec/smdx_65534.xml
epcpm/tests/test_c.py
epcpm/tests/test_canmodel.py
epcpm/tests/test_canmodel_parametermodel.json
epcpm/tests/test_cantosym.py
epcpm/tests/test_importexportdialog.py
epcpm/tests/test_parameters.py
epcpm/tests/test_parameterstoc.py
epcpm/tests/test_parameterstohierarchy.py
epcpm/tests/test_project.py
epcpm/tests/test_roundtrip.py
epcpm/tests/test_smdxtosunspec.py
epcpm/tests/test_staticmodbusmodel.py
epcpm/tests/test_sunspecmodel.py
epcpm-2022.1.9.dist-info/entry_points.txt
epcpm-2022.1.9.dist-info/WHEEL
epcpm-2022.1.9.dist-info/METADATA
epcpm-2022.1.9.dist-info/RECORD
