Metadata-Version: 2.1
Name: epcpm
Version: 2022.1.9
Summary: 
Author: Alex Anker
Author-email: alex.anker@epcpower.com
Requires-Python: >=3.7,<4.0
Classifier: Programming Language :: Python :: 3
Classifier: Programming Language :: Python :: 3.10
Classifier: Programming Language :: Python :: 3.7
Classifier: Programming Language :: Python :: 3.8
Classifier: Programming Language :: Python :: 3.9
Requires-Dist: Jinja2 (>=3.0.3,<4.0.0)
Requires-Dist: PyQt5 (==5.13.2)
Requires-Dist: Twisted (==21.2.0)
Requires-Dist: attrs (==20.2.0)
Requires-Dist: canmatrix (==0.9.1)
Requires-Dist: click (>=7.0.0,<8.0.0)
Requires-Dist: codecov (>=2.1.12,<3.0.0)
Requires-Dist: graham (==0.1.11)
Requires-Dist: lxml (==4.3.0)
Requires-Dist: openpyxl (==2.5.12)
Requires-Dist: pycparser (==2.21)
Requires-Dist: pyserial (==3.4)
Requires-Dist: pysunspec (>=2.1.1,<3.0.0)
Requires-Dist: pytest (==3.8.2)
Requires-Dist: pytest-cov (==2.5.1)
Requires-Dist: pytest-qt (==3.2.1)
Requires-Dist: pytest-twisted (==1.9)
Requires-Dist: python-can (>=3.3.4,<4.0.0)
Requires-Dist: requests (==2.26.0)
Requires-Dist: sunspecdemo (>=0.1.9,<0.2.0)
Requires-Dist: toolz (==0.9.0)
Requires-Dist: tox (==2.8.2)
Requires-Dist: twine (==1.13.0)
Requires-Dist: xmldiff (==2.2)
